bedrock_protocol/packets/__init__.py
bedrock_protocol/packets/minecraft_packet_ids.py
bedrock_protocol/packets/minecraft_packets.py
bedrock_protocol/packets/shared_constants.py
bedrock_protocol/packets/enums/__init__.py
bedrock_protocol/packets/enums/item_stack_request_action_type.py
bedrock_protocol/packets/enums/level_sound_event.py
bedrock_protocol/packets/packet/__init__.py
bedrock_protocol/packets/packet/block_actor_data_packet.py
bedrock_protocol/packets/packet/container_close_packet.py
bedrock_protocol/packets/packet/container_open_packet.py
bedrock_protocol/packets/packet/item_registry_packet.py
bedrock_protocol/packets/packet/item_stack_request_packet.py
bedrock_protocol/packets/packet/level_sound_event_packet.py
bedrock_protocol/packets/packet/packet_base.py
bedrock_protocol/packets/packet/remove_actor_packet.py
bedrock_protocol/packets/packet/unimplemented_packet.py
bedrock_protocol/packets/packet/update_block_packet.py
bedrock_protocol/packets/types/__init__.py
bedrock_protocol/packets/types/block_pos.py
bedrock_protocol/packets/types/full_container_name.py
bedrock_protocol/packets/types/item_data.py
bedrock_protocol/packets/types/item_stack_request.py
bedrock_protocol/packets/types/mce_uuid.py
bedrock_protocol/packets/types/network_position.py
bedrock_protocol/packets/types/vec3.py
bedrock_protocol_packets-0.0.6.dist-info/licenses/LICENSE
tests/test.py
tests/uuid_test.py
bedrock_protocol_packets-0.0.6.dist-info/METADATA
bedrock_protocol_packets-0.0.6.dist-info/WHEEL
bedrock_protocol_packets-0.0.6.dist-info/top_level.txt
bedrock_protocol_packets-0.0.6.dist-info/RECORD
