Metadata-Version: 2.4
Name: bedrock-protocol-packets
Version: 0.0.6
Summary: Minecraft Bedrock Packets Codec Library
Author: GlacieTeam
License: MPL-2.0
Project-URL: homepage, https://github.com/GlacieTeam/bedrock-protocol-packets
Classifier: Programming Language :: Python :: 3
Classifier: License :: OSI Approved :: Mozilla Public License 2.0 (MPL 2.0)
Classifier: Operating System :: OS Independent
Requires-Python: >=3.8
License-File: LICENSE
Requires-Dist: bstream>=1.0.0
Requires-Dist: rapidnbt>=1.1.3
Dynamic: license-file
